{
	"name": "block",
	"version": "0.2.0",
	"homepage": "https://github.com/dominikwilkowski/cfonts",
	"colors": 2,
	"lines": 6,
	"buffer": [
		"",
		"",
		"",
		"",
		"",
		""
	],
	"letterspace": [
		" ",
		" ",
		" ",
		" ",
		" ",
		" "
	],
	"letterspace_size": 1,
	"chars": {
		"A": [
			" <c1>█████</c1><c2>╗</c2> ",
			"<c1>██</c1><c2>╔══</c2><c1>██</c1><c2>╗</c2>",
			"<c1>███████</c1><c2>║</c2>",
			"<c1>██</c1><c2>╔══</c2><c1>██</c1><c2>║</c2>",
			"<c1>██</c1><c2>║</c2><c1>  ██</c1><c2>║</c2>",
			"<c2>╚═╝  ╚═╝</c2>"
		],
		"B": [
			"<c1>██████</c1><c2>╗ </c2>",
			"<c1>██</c1><c2>╔══</c2><c1>██</c1><c2>╗</c2>",
			"<c1>██████</c1><c2>╔╝</c2>",
			"<c1>██</c1><c2>╔══</c2><c1>██</c1><c2>╗</c2>",
			"<c1>██████</c1><c2>╔╝</c2>",
			"<c2>╚═════╝ </c2>"
		],
		"C": [
			" <c1>██████</c1><c2>╗</c2>",
			"<c1>██</c1><c2>╔════╝</c2>",
			"<c1>██</c1><c2>║     </c2>",
			"<c1>██</c1><c2>║     </c2>",
			"<c2>╚</c2><c1>██████</c1><c2>╗</c2>",
			"<c2> ╚═════╝</c2>"
		],
		"D": [
			"<c1>██████</c1><c2>╗ </c2>",
			"<c1>██</c1><c2>╔══</c2><c1>██</c1><c2>╗</c2>",
			"<c1>██</c1><c2>║</c2><c1>  ██</c1><c2>║</c2>",
			"<c1>██</c1><c2>║</c2><c1>  ██</c1><c2>║</c2>",
			"<c1>██████</c1><c2>╔╝</c2>",
			"<c2>╚═════╝ </c2>"
		],
		"E": [
			"<c1>███████</c1><c2>╗</c2>",
			"<c1>██</c1><c2>╔════╝</c2>",
			"<c1>█████</c1><c2>╗  </c2>",
			"<c1>██</c1><c2>╔══╝  </c2>",
			"<c1>███████</c1><c2>╗</c2>",
			"<c2>╚══════╝</c2>"
		],
		"F": [
			"<c1>███████</c1><c2>╗</c2>",
			"<c1>██</c1><c2>╔════╝</c2>",
			"<c1>█████</c1><c2>╗  </c2>",
			"<c1>██</c1><c2>╔══╝  </c2>",
			"<c1>██</c1><c2>║     </c2>",
			"<c2>╚═╝     </c2>"
		],
		"G": [
			" <c1>██████</c1><c2>╗ </c2>",
			"<c1>██</c1><c2>╔════╝ </c2>",
			"<c1>██</c1><c2>║</c2><c1>  ███</c1><c2>╗</c2>",
			"<c1>██</c1><c2>║</c2><c1>   ██</c1><c2>║</c2>",
			"<c2>╚</c2><c1>██████</c1><c2>╔╝</c2>",
			"<c2> ╚═════╝ </c2>"
		],
		"H": [
			"<c1>██</c1><c2>╗</c2><c1>  ██</c1><c2>╗</c2>",
			"<c1>██</c1><c2>║</c2><c1>  ██</c1><c2>║</c2>",
			"<c1>███████</c1><c2>║</c2>",
			"<c1>██</c1><c2>╔══</c2><c1>██</c1><c2>║</c2>",
			"<c1>██</c1><c2>║</c2><c1>  ██</c1><c2>║</c2>",
			"<c2>╚═╝  ╚═╝</c2>"
		],
		"I": [
			"<c1>██</c1><c2>╗</c2>",
			"<c1>██</c1><c2>║</c2>",
			"<c1>██</c1><c2>║</c2>",
			"<c1>██</c1><c2>║</c2>",
			"<c1>██</c1><c2>║</c2>",
			"<c2>╚═╝</c2>"
		],
		"J": [
			"<c1>     ██</c1><c2>╗</c2>",
			"<c1>     ██</c1><c2>║</c2>",
			"<c1>     ██</c1><c2>║</c2>",
			"<c1>██   ██</c1><c2>║</c2>",
			"<c2>╚</c2><c1>█████</c1><c2>╔╝</c2>",
			"<c2> ╚════╝ </c2>"
		],
		"K": [
			"<c1>██</c1><c2>╗</c2><c1>  ██</c1><c2>╗</c2>",
			"<c1>██</c1><c2>║</c2><c1> ██</c1><c2>╔╝</c2>",
			"<c1>█████</c1><c2>╔╝ </c2>",
			"<c1>██</c1><c2>╔═</c2><c1>██</c1><c2>╗ </c2>",
			"<c1>██</c1><c2>║</c2><c1>  ██</c1><c2>╗</c2>",
			"<c2>╚═╝  ╚═╝</c2>"
		],
		"L": [
			"<c1>██</c1><c2>╗     </c2>",
			"<c1>██</c1><c2>║     </c2>",
			"<c1>██</c1><c2>║     </c2>",
			"<c1>██</c1><c2>║     </c2>",
			"<c1>███████</c1><c2>╗</c2>",
			"<c2>╚══════╝</c2>"
		],
		"M": [
			"<c1>███</c1><c2>╗</c2><c1>   ███</c1><c2>╗</c2>",
			"<c1>████</c1><c2>╗</c2><c1> ████</c1><c2>║</c2>",
			"<c1>██</c1><c2>╔</c2><c1>████</c1><c2>╔</c2><c1>██</c1><c2>║</c2>",
			"<c1>██</c1><c2>║╚</c2><c1>██</c1><c2>╔╝</c2><c1>██</c1><c2>║</c2>",
			"<c1>██</c1><c2>║ ╚═╝</c2><c1> ██</c1><c2>║</c2>",
			"<c2>╚═╝     ╚═╝</c2>"
		],
		"N": [
			"<c1>███</c1><c2>╗</c2><c1>   ██</c1><c2>╗</c2>",
			"<c1>████</c1><c2>╗</c2><c1>  ██</c1><c2>║</c2>",
			"<c1>██</c1><c2>╔</c2><c1>██</c1><c2>╗</c2><c1> ██</c1><c2>║</c2>",
			"<c1>██</c1><c2>║╚</c2><c1>██</c1><c2>╗</c2><c1>██</c1><c2>║</c2>",
			"<c1>██</c1><c2>║ ╚</c2><c1>████</c1><c2>║</c2>",
			"<c2>╚═╝  ╚═══╝</c2>"
		],
		"O": [
			" <c1>██████</c1><c2>╗ </c2>",
			"<c1>██</c1><c2>╔═══</c2><c1>██</c1><c2>╗</c2>",
			"<c1>██</c1><c2>║</c2><c1>   ██</c1><c2>║</c2>",
			"<c1>██</c1><c2>║</c2><c1>   ██</c1><c2>║</c2>",
			"<c2>╚</c2><c1>██████</c1><c2>╔╝</c2>",
			"<c2> ╚═════╝ </c2>"
		],
		"P": [
			"<c1>██████</c1><c2>╗ </c2>",
			"<c1>██</c1><c2>╔══</c2><c1>██</c1><c2>╗</c2>",
			"<c1>██████</c1><c2>╔╝</c2>",
			"<c1>██</c1><c2>╔═══╝ </c2>",
			"<c1>██</c1><c2>║     </c2>",
			"<c2>╚═╝     </c2>"
		],
		"Q": [
			" <c1>██████</c1><c2>╗ </c2>",
			"<c1>██</c1><c2>╔═══</c2><c1>██</c1><c2>╗</c2>",
			"<c1>██</c1><c2>║</c2><c1>   ██</c1><c2>║</c2>",
			"<c1>██</c1><c2>║</c2><c1>▄▄ ██</c1><c2>║</c2>",
			"<c2>╚</c2><c1>██████</c1><c2>╔╝</c2>",
			"<c2> ╚══</c2><c1>▀▀</c1><c2>═╝ </c2>"
		],
		"R": [
			"<c1>██████</c1><c2>╗ </c2>",
			"<c1>██</c1><c2>╔══</c2><c1>██</c1><c2>╗</c2>",
			"<c1>██████</c1><c2>╔╝</c2>",
			"<c1>██</c1><c2>╔══</c2><c1>██</c1><c2>╗</c2>",
			"<c1>██</c1><c2>║</c2><c1>  ██</c1><c2>║</c2>",
			"<c2>╚═╝  ╚═╝</c2>"
		],
		"S": [
			"<c1>███████</c1><c2>╗</c2>",
			"<c1>██</c1><c2>╔════╝</c2>",
			"<c1>███████</c1><c2>╗</c2>",
			"<c2>╚════</c2><c1>██</c1><c2>║</c2>",
			"<c1>███████</c1><c2>║</c2>",
			"<c2>╚══════╝</c2>"
		],
		"T": [
			"<c1>████████</c1><c2>╗</c2>",
			"<c2>╚══</c2><c1>██</c1><c2>╔══╝</c2>",
			"<c1>   ██</c1><c2>║   </c2>",
			"<c1>   ██</c1><c2>║   </c2>",
			"<c1>   ██</c1><c2>║   </c2>",
			"<c2>   ╚═╝   </c2>"
		],
		"U": [
			"<c1>██</c1><c2>╗</c2><c1>   ██</c1><c2>╗</c2>",
			"<c1>██</c1><c2>║</c2><c1>   ██</c1><c2>║</c2>",
			"<c1>██</c1><c2>║</c2><c1>   ██</c1><c2>║</c2>",
			"<c1>██</c1><c2>║</c2><c1>   ██</c1><c2>║</c2>",
			"<c2>╚</c2><c1>██████</c1><c2>╔╝</c2>",
			"<c2> ╚═════╝ </c2>"
		],
		"V": [
			"<c1>██</c1><c2>╗</c2><c1>   ██</c1><c2>╗</c2>",
			"<c1>██</c1><c2>║</c2><c1>   ██</c1><c2>║</c2>",
			"<c1>██</c1><c2>║</c2><c1>   ██</c1><c2>║</c2>",
			"<c2>╚</c2><c1>██</c1><c2>╗</c2><c1> ██</c1><c2>╔╝</c2>",
			"<c2> ╚</c2><c1>████</c1><c2>╔╝ </c2>",
			"<c2>  ╚═══╝  </c2>"
		],
		"W": [
			"<c1>██</c1><c2>╗    </c2><c1>██</c1><c2>╗</c2>",
			"<c1>██</c1><c2>║    </c2><c1>██</c1><c2>║</c2>",
			"<c1>██</c1><c2>║</c2><c1> █</c1><c2>╗</c2><c1> ██</c1><c2>║</c2>",
			"<c1>██</c1><c2>║</c2><c1>███</c1><c2>╗</c2><c1>██</c1><c2>║</c2>",
			"<c2>╚</c2><c1>███</c1><c2>╔</c2><c1>███</c1><c2>╔╝</c2>",
			"<c2> ╚══╝╚══╝ </c2>"
		],
		"X": [
			"<c1>██</c1><c2>╗</c2><c1>  ██</c1><c2>╗</c2>",
			"<c2>╚</c2><c1>██</c1><c2>╗</c2><c1>██</c1><c2>╔╝</c2>",
			"<c2> ╚</c2><c1>███</c1><c2>╔╝ </c2>",
			" <c1>██</c1><c2>╔</c2><c1>██</c1><c2>╗ </c2>",
			"<c1>██</c1><c2>╔╝</c2><c1> ██</c1><c2>╗</c2>",
			"<c2>╚═╝  ╚═╝</c2>"
		],
		"Y": [
			"<c1>██</c1><c2>╗</c2><c1>   ██</c1><c2>╗</c2>",
			"<c2>╚</c2><c1>██</c1><c2>╗</c2><c1> ██</c1><c2>╔╝</c2>",
			"<c2> ╚</c2><c1>████</c1><c2>╔╝ </c2>",
			"<c2>  ╚</c2><c1>██</c1><c2>╔╝  </c2>",
			"<c1>   ██</c1><c2>║   </c2>",
			"<c2>   ╚═╝   </c2>"
		],
		"Z": [
			"<c1>███████</c1><c2>╗</c2>",
			"<c2>╚══</c2><c1>███</c1><c2>╔╝</c2>",
			"<c1>  ███</c1><c2>╔╝ </c2>",
			" <c1>███</c1><c2>╔╝  </c2>",
			"<c1>███████</c1><c2>╗</c2>",
			"<c2>╚══════╝</c2>"
		],
		"0": [
			" <c1>██████</c1><c2>╗ </c2>",
			"<c1>██</c1><c2>╔═</c2><c1>████</c1><c2>╗</c2>",
			"<c1>██</c1><c2>║</c2><c1>██</c1><c2>╔</c2><c1>██</c1><c2>║</c2>",
			"<c1>████</c1><c2>╔╝</c2><c1>██</c1><c2>║</c2>",
			"<c2>╚</c2><c1>██████</c1><c2>╔╝</c2>",
			"<c2> ╚═════╝ </c2>"
		],
		"1": [
			" <c1>██</c1><c2>╗</c2>",
			"<c1>███</c1><c2>║</c2>",
			"<c2>╚</c2><c1>██</c1><c2>║</c2>",
			" <c1>██</c1><c2>║</c2>",
			" <c1>██</c1><c2>║</c2>",
			"<c2> ╚═╝</c2>"
		],
		"2": [
			"<c1>██████</c1><c2>╗ </c2>",
			"<c2>╚════</c2><c1>██</c1><c2>╗</c2>",
			" <c1>█████</c1><c2>╔╝</c2>",
			"<c1>██</c1><c2>╔═══╝ </c2>",
			"<c1>███████</c1><c2>╗</c2>",
			"<c2>╚══════╝</c2>"
		],
		"3": [
			"<c1>██████</c1><c2>╗ </c2>",
			"<c2>╚════</c2><c1>██</c1><c2>╗</c2>",
			" <c1>█████</c1><c2>╔╝</c2>",
			"<c2> ╚═══</c2><c1>██</c1><c2>╗</c2>",
			"<c1>██████</c1><c2>╔╝</c2>",
			"<c2>╚═════╝ </c2>"
		],
		"4": [
			"<c1>██</c1><c2>╗</c2><c1>  ██</c1><c2>╗</c2>",
			"<c1>██</c1><c2>║</c2><c1>  ██</c1><c2>║</c2>",
			"<c1>███████</c1><c2>║</c2>",
			"<c2>╚════</c2><c1>██</c1><c2>║</c2>",
			"<c1>     ██</c1><c2>║</c2>",
			"<c2>     ╚═╝</c2>"
		],
		"5": [
			"<c1>███████</c1><c2>╗</c2>",
			"<c1>██</c1><c2>╔════╝</c2>",
			"<c1>███████</c1><c2>╗</c2>",
			"<c2>╚════</c2><c1>██</c1><c2>║</c2>",
			"<c1>███████</c1><c2>║</c2>",
			"<c2>╚══════╝</c2>"
		],
		"6": [
			" <c1>██████</c1><c2>╗ </c2>",
			"<c1>██</c1><c2>╔════╝ </c2>",
			"<c1>███████</c1><c2>╗ </c2>",
			"<c1>██</c1><c2>╔═══</c2><c1>██</c1><c2>╗</c2>",
			"<c2>╚</c2><c1>██████</c1><c2>╔╝</c2>",
			"<c2> ╚═════╝ </c2>"
		],
		"7": [
			"<c1>███████</c1><c2>╗</c2>",
			"<c2>╚════</c2><c1>██</c1><c2>║</c2>",
			"<c1>    ██</c1><c2>╔╝</c2>",
			"<c1>   ██</c1><c2>╔╝ </c2>",
			"<c1>   ██</c1><c2>║  </c2>",
			"<c2>   ╚═╝  </c2>"
		],
		"8": [
			" <c1>█████</c1><c2>╗ </c2>",
			"<c1>██</c1><c2>╔══</c2><c1>██</c1><c2>╗</c2>",
			"<c2>╚</c2><c1>█████</c1><c2>╔╝</c2>",
			"<c1>██</c1><c2>╔══</c2><c1>██</c1><c2>╗</c2>",
			"<c2>╚</c2><c1>█████</c1><c2>╔╝</c2>",
			"<c2> ╚════╝ </c2>"
		],
		"9": [
			" <c1>█████</c1><c2>╗ </c2>",
			"<c1>██</c1><c2>╔══</c2><c1>██</c1><c2>╗</c2>",
			"<c2>╚</c2><c1>██████</c1><c2>║</c2>",
			"<c2> ╚═══</c2><c1>██</c1><c2>║</c2>",
			" <c1>█████</c1><c2>╔╝</c2>",
			"<c2> ╚════╝ </c2>"
		],
		"!": [
			"<c1>██</c1><c2>╗</c2>",
			"<c1>██</c1><c2>║</c2>",
			"<c1>██</c1><c2>║</c2>",
			"<c2>╚═╝</c2>",
			"<c1>██</c1><c2>╗</c2>",
			"<c2>╚═╝</c2>"
		],
		"?": [
			"<c1>██████</c1><c2>╗ </c2>",
			"<c2>╚════</c2><c1>██</c1><c2>╗</c2>",
			"<c1>  ▄███</c1><c2>╔╝</c2>",
			"<c1>  ▀▀</c1><c2>══╝ </c2>",
			"<c1>  ██</c1><c2>╗   </c2>",
			"<c2>  ╚═╝   </c2>"
		],
		".": [
			"   ",
			"   ",
			"   ",
			"   ",
			"<c1>██</c1><c2>╗</c2>",
			"<c2>╚═╝</c2>"
		],
		"+": [
			"       ",
			"<c1>  ██</c1><c2>╗  </c2>",
			"<c1>██████</c1><c2>╗</c2>",
			"<c2> ╚</c2><c1>██</c1><c2>╔═╝</c2>",
			"<c2>  ╚═╝  </c2>",
			"       "
		],
		"-": [
			"      ",
			"      ",
			"<c1>█████</c1><c2>╗</c2>",
			"<c2>╚════╝</c2>",
			"      ",
			"      "
		],
		"_": [
			"        ",
			"        ",
			"        ",
			"        ",
			"<c1>███████</c1><c2>╗</c2>",
			"<c2>╚══════╝</c2>"
		],
		"=": [
			"       ",
			"<c1>██████</c1><c2>╗</c2>",
			"<c2>╚═════╝</c2>",
			"<c1>██████</c1><c2>╗</c2>",
			"<c2>╚═════╝</c2>",
			"       "
		],
		"@": [
			" <c1>██████</c1><c2>╗ </c2>",
			"<c1>██</c1><c2>╔═══</c2><c1>██</c1><c2>╗</c2>",
			"<c1>██</c1><c2>║</c2><c1>██</c1><c2>╗</c2><c1>██</c1><c2>║</c2>",
			"<c1>██</c1><c2>║</c2><c1>██</c1><c2>║</c2><c1>██</c1><c2>║</c2>",
			"<c2>╚</c2><c1>█</c1><c2>║</c2><c1>████</c1><c2>╔╝</c2>",
			"<c2> ╚╝╚═══╝ </c2>"
		],
		"#": [
			" <c1>██</c1><c2>╗</c2><c1> ██</c1><c2>╗ </c2>",
			"<c1>████████</c1><c2>╗</c2>",
			"<c2>╚</c2><c1>██</c1><c2>╔═</c2><c1>██</c1><c2>╔╝</c2>",
			"<c1>████████</c1><c2>╗</c2>",
			"<c2>╚</c2><c1>██</c1><c2>╔═</c2><c1>██</c1><c2>╔╝</c2>",
			"<c2> ╚═╝ ╚═╝ </c2>"
		],
		"$": [
			"<c1>▄▄███▄▄</c1><c2>·</c2>",
			"<c1>██</c1><c2>╔════╝</c2>",
			"<c1>███████</c1><c2>╗</c2>",
			"<c2>╚════</c2><c1>██</c1><c2>║</c2>",
			"<c1>███████</c1><c2>║</c2>",
			"<c2>╚═</c2><c1>▀▀▀</c1><c2>══╝</c2>"
		],
		"%": [
			"<c1>██</c1><c2>╗</c2><c1> ██</c1><c2>╗</c2>",
			"<c2>╚═╝</c2><c1>██</c1><c2>╔╝</c2>",
			"<c1>  ██</c1><c2>╔╝ </c2>",
			" <c1>██</c1><c2>╔╝  </c2>",
			"<c1>██</c1><c2>╔╝</c2><c1>██</c1><c2>╗</c2>",
			"<c2>╚═╝ ╚═╝</c2>"
		],
		"&": [
			"<c1>   ██</c1><c2>╗   </c2>",
			"<c1>   ██</c1><c2>║   </c2>",
			"<c1>████████</c1><c2>╗</c2>",
			"<c1>██</c1><c2>╔═</c2><c1>██</c1><c2>╔═╝</c2>",
			"<c1>██████</c1><c2>║  </c2>",
			"<c2>╚═════╝  </c2>"
		],
		"(": [
			" <c1>██</c1><c2>╗</c2>",
			"<c1>██</c1><c2>╔╝</c2>",
			"<c1>██</c1><c2>║ ",
			"<c1>██</c1><c2>║ ",
			"<c2>╚</c2><c1>██</c1><c2>╗</c2>",
			"<c2> ╚═╝</c2>"
		],
		")": [
			"<c1>██</c1><c2>╗ </c2>",
			"<c2>╚</c2><c1>██</c1><c2>╗</c2>",
			" <c1>██</c1><c2>║</c2>",
			" <c1>██</c1><c2>║</c2>",
			"<c1>██</c1><c2>╔╝</c2>",
			"<c2>╚═╝ </c2>"
		],
		"/": [
			"<c1>    ██</c1><c2>╗</c2>",
			"<c1>   ██</c1><c2>╔╝</c2>",
			"<c1>  ██</c1><c2>╔╝ </c2>",
			" <c1>██</c1><c2>╔╝  </c2>",
			"<c1>██</c1><c2>╔╝   </c2>",
			"<c2>╚═╝    </c2>"
		],
		":": [
			"   ",
			"<c1>██</c1><c2>╗</c2>",
			"<c2>╚═╝</c2>",
			"<c1>██</c1><c2>╗</c2>",
			"<c2>╚═╝</c2>",
			"   "
		],
		";": [
			"   ",
			"   ",
			"<c1>██</c1><c2>╗</c2>",
			"<c2>╚═╝</c2>",
			"<c1>▄█</c1><c2>╗</c2>",
			"<c1>▀</c1><c2>═╝</c2>"
		],
		",": [
			"   ",
			"   ",
			"   ",
			"   ",
			"<c1>▄█</c1><c2>╗</c2>",
			"<c1>▀</c1><c2>═╝</c2>"
		],
		"'": [
			"<c1>█</c1><c2>╗</c2> ",
			"<c2>╚╝</c2> ",
			"   ",
			"   ",
			"   ",
			"   "
		],
		"\"": [
			"<c1>█</c1><c2>╗</c2><c1>█</c1><c2>╗</c2> ",
			"<c2>╚╝╚╝</c2> ",
			"     ",
			"     ",
			"     ",
			"     "
		],
		" ": [
			"   ",
			"   ",
			"   ",
			"   ",
			"   ",
			"   "
		]
	}
}
